py_rodo/__init__.py
py_rodo/callback.py
py_rodo/py.typed
py_rodo/types.py
py_rodo-0.0.1.dist-info/METADATA
py_rodo-0.0.1.dist-info/WHEEL
py_rodo-0.0.1.dist-info/entry_points.txt
py_rodo-0.0.1.dist-info/RECORD
