Metadata-Version: 2.1
Name: py-rodo
Version: 0.0.1
Summary: Helper library to process messages on rabbit.opensuse.org
License: LGPL-2.1-or-later
Author: Dan Čermák
Author-email: dcermak@suse.com
Requires-Python: >=3.10,<4.0
Classifier: License :: OSI Approved
Classifier: Programming Language :: Python :: 3
Classifier: Programming Language :: Python :: 3.10
Classifier: Programming Language :: Python :: 3.11
Classifier: Programming Language :: Python :: 3.12
Classifier: Programming Language :: Python :: 3.13
Requires-Dist: dataclassy (>=1.0.1)
Requires-Dist: pika (>=1.3.2)
